LICENSE
MANIFEST.in
README.md
setup.py
exeLauncher/__init__.py
exeLauncher/__main__.py
exeLauncher/exeLauncher.py
exeLauncher.egg-info/PKG-INFO
exeLauncher.egg-info/SOURCES.txt
exeLauncher.egg-info/dependency_links.txt
exeLauncher.egg-info/top_level.txt