Metadata-Version: 2.1
Name: exeLauncher
Version: 1.0.0
Summary: All this does is launch .exe files directly from the command prompt, lol.
Home-page: UNKNOWN
Author: Fruitsy
License: UNKNOWN
Platform: UNKNOWN
Classifier: Programming Language :: Python :: 3
Classifier: License :: OSI Approved :: MIT License
Classifier: Operating System :: OS Independent
Requires-Python: >=3.6
